MANIFEST.in
README.md
setup.py
CKMobile.egg-info/PKG-INFO
CKMobile.egg-info/SOURCES.txt
CKMobile.egg-info/dependency_links.txt
CKMobile.egg-info/requires.txt
CKMobile.egg-info/top_level.txt
src/CKMobile/__init__.py