Metadata-Version: 1.0
Name: CKMobile
Version: 0.0.1b2
Summary: ChokChaisak
Home-page: https://github.com/ChokChaisak/ChokChaisak
Author: ChokChaisak
Author-email: ChokChaisak@gmail.com
License: ChokChaisak
Keywords: CKMobile
Platform: UNKNOWN
